{"contributors": null, "coordinates": null, "created_at": "Tue Apr 16 00:42:55 +0000 2013", "display_text_range": [0, 105], "entities": {"hashtags": [{"indices": [91, 105], "text": "prayforboston"}], "symbols": [], "urls": [], "user_mentions": [{"id": 822215673812119600, "id_str": "822215673812119553", "indices": [1, 12], "name": "The White House", "screen_name": "WhiteHouse"}]}, "favorite_count": 0, "favorited": false, "full_text": "\u201c@whitehouse: President Obama: \"Boston is a tough and resilient town. So are its people.\"\u201d #prayforboston", "geo": null, "id": 323959657272061950, "id_str": "323959657272061952", "in_reply_to_screen_name": "ObamaWhiteHouse", "in_reply_to_status_id": 323921953931014140, "in_reply_to_status_id_str": "323921953931014146", "in_reply_to_user_id": 30313925, "in_reply_to_user_id_str": "30313925", "is_quote_status": false, "lang": "en", "place": null, "retweet_count": 0, "retweeted": false, "source": "<a href=\"http://twitter.com/download/iphone\" rel=\"nofollow\">Twitter for iPhone</a>", "truncated": false, "user": {"contributors_enabled": false, "created_at": "Tue Oct 02 16:48:54 +0000 2012", "default_profile": false, "default_profile_image": false, "description": "Community Health Improvement Coordinator. Avid news reader, music listener, and feminist.", "entities": {"description": {"urls": []}}, "favourites_count": 663, "follow_request_sent": false, "followers_count": 87, "following": false, "friends_count": 224, "geo_enabled": true, "has_extended_profile": false, "id": 858351512, "id_str": "858351512", "is_translation_enabled": false, "is_translator": false, "lang": null, "listed_count": 3, "location": "Tillamook, OR", "name": "Heather Oberst", "notifications": false, "profile_background_color": "EDECE9", "profile_background_image_url": "http://abs.twimg.com/images/themes/theme3/bg.gif", "profile_background_image_url_https": "https://abs.twimg.com/images/themes/theme3/bg.gif", "profile_background_tile": false, "profile_banner_url": "https://pbs.twimg.com/profile_banners/858351512/1398441704", "profile_image_url": "http://pbs.twimg.com/profile_images/784445470290489344/iSpEZeOn_normal.jpg", "profile_image_url_https": "https://pbs.twimg.com/profile_images/784445470290489344/iSpEZeOn_normal.jpg", "profile_link_color": "088253", "profile_sidebar_border_color": "D3D2CF", "profile_sidebar_fill_color": "E3E2DE", "profile_text_color": "634047", "profile_use_background_image": true, "protected": false, "screen_name": "HeatheronHealth", "statuses_count": 464, "time_zone": null, "translator_type": "none", "url": null, "utc_offset": null, "verified": false}}