{"contributors": null, "coordinates": null, "created_at": "Sat Jan 10 06:21:29 +0000 2015", "display_text_range": [0, 55], "entities": {"hashtags": [], "symbols": [], "urls": [], "user_mentions": [{"id": 3064269879, "id_str": "3064269879", "indices": [0, 16], "name": "The Sun", "screen_name": "thesunnewspaper"}]}, "favorite_count": 0, "favorited": false, "full_text": "@TheSunNewspaper rimenal terrarist not rights to alaive", "geo": null, "id": 553798764507324400, "id_str": "553798764507324417", "in_reply_to_screen_name": "TheSun", "in_reply_to_status_id": 553503313116033000, "in_reply_to_status_id_str": "553503313116033025", "in_reply_to_user_id": 34655603, "in_reply_to_user_id_str": "34655603", "is_quote_status": false, "lang": "en", "place": null, "retweet_count": 0, "retweeted": false, "source": "<a href=\"http://twitter.com/download/android\" rel=\"nofollow\">Twitter for Android</a>", "truncated": false, "user": {"contributors_enabled": false, "created_at": "Sat Jul 26 14:37:25 +0000 2014", "default_profile": true, "default_profile_image": false, "description": "", "entities": {"description": {"urls": []}}, "favourites_count": 11, "follow_request_sent": false, "followers_count": 1, "following": false, "friends_count": 59, "geo_enabled": true, "has_extended_profile": false, "id": 2682527221, "id_str": "2682527221", "is_translation_enabled": false, "is_translator": false, "lang": null, "listed_count": 0, "location": "", "name": "Shivaraj Spandana", "notifications": false, "profile_background_color": "C0DEED", "profile_background_image_url": "http://abs.twimg.com/images/themes/theme1/bg.png", "profile_background_image_url_https": "https://abs.twimg.com/images/themes/theme1/bg.png", "profile_background_tile": false, "profile_banner_url": "https://pbs.twimg.com/profile_banners/2682527221/1451529512", "profile_image_url": "http://pbs.twimg.com/profile_images/682390356277596160/ZYsYqj3d_normal.jpg", "profile_image_url_https": "https://pbs.twimg.com/profile_images/682390356277596160/ZYsYqj3d_normal.jpg", "profile_link_color": "1DA1F2", "profile_sidebar_border_color": "C0DEED", "profile_sidebar_fill_color": "DDEEF6", "profile_text_color": "333333", "profile_use_background_image": true, "protected": false, "screen_name": "shivarajspanda", "statuses_count": 80, "time_zone": null, "translator_type": "none", "url": null, "utc_offset": null, "verified": false}}