{"contributors": null, "coordinates": null, "created_at": "Tue Apr 16 01:53:45 +0000 2013", "display_text_range": [0, 16], "entities": {"hashtags": [], "symbols": [], "urls": [], "user_mentions": [{"id": 245992215, "id_str": "245992215", "indices": [0, 7], "name": "Fergie", "screen_name": "Fergie"}]}, "favorite_count": 0, "favorited": false, "full_text": "@Fergie thanks!!", "geo": null, "id": 323977480581038100, "id_str": "323977480581038081", "in_reply_to_screen_name": "Fergie", "in_reply_to_status_id": 323962098344411140, "in_reply_to_status_id_str": "323962098344411138", "in_reply_to_user_id": 245992215, "in_reply_to_user_id_str": "245992215", "is_quote_status": false, "lang": "en", "place": null, "retweet_count": 0, "retweeted": false, "source": "<a href=\"http://twitter.com\" rel=\"nofollow\">Twitter Web Client</a>", "truncated": false, "user": {"contributors_enabled": false, "created_at": "Mon Apr 15 22:30:50 +0000 2013", "default_profile": true, "default_profile_image": false, "description": "", "entities": {"description": {"urls": []}}, "favourites_count": 102, "follow_request_sent": false, "followers_count": 14, "following": false, "friends_count": 79, "geo_enabled": false, "has_extended_profile": false, "id": 1355497964, "id_str": "1355497964", "is_translation_enabled": false, "is_translator": false, "lang": null, "listed_count": 0, "location": "", "name": "Gabriel Contreras", "notifications": false, "profile_background_color": "C0DEED", "profile_background_image_url": "http://abs.twimg.com/images/themes/theme1/bg.png", "profile_background_image_url_https": "https://abs.twimg.com/images/themes/theme1/bg.png", "profile_background_tile": false, "profile_image_url": "http://pbs.twimg.com/profile_images/3528263040/9e27c4c74cd6efe5b0bf88527ca39573_normal.jpeg", "profile_image_url_https": "https://pbs.twimg.com/profile_images/3528263040/9e27c4c74cd6efe5b0bf88527ca39573_normal.jpeg", "profile_link_color": "1DA1F2", "profile_sidebar_border_color": "C0DEED", "profile_sidebar_fill_color": "DDEEF6", "profile_text_color": "333333", "profile_use_background_image": true, "protected": false, "screen_name": "Contrers_1", "statuses_count": 69, "time_zone": null, "translator_type": "none", "url": null, "utc_offset": null, "verified": false}}