{"contributors": null, "coordinates": null, "created_at": "Thu Jan 08 08:57:58 +0000 2015", "display_text_range": [0, 131], "entities": {"hashtags": [{"indices": [39, 52], "text": "CharlieHebdo"}], "media": [{"display_url": "pic.twitter.com/2iqNZDfnEK", "expanded_url": "https://twitter.com/MailOnline/status/553108804934856704/photo/1", "id": 553108548968644600, "id_str": "553108548968644608", "indices": [108, 130], "media_url": "http://pbs.twimg.com/media/B60JS3eCAAAXCiC.jpg", "media_url_https": "https://pbs.twimg.com/media/B60JS3eCAAAXCiC.jpg", "sizes": {"large": {"h": 656, "resize": "fit", "w": 962}, "medium": {"h": 656, "resize": "fit", "w": 962}, "small": {"h": 464, "resize": "fit", "w": 680}, "thumb": {"h": 150, "resize": "crop", "w": 150}}, "source_status_id": 553108804934856700, "source_status_id_str": "553108804934856704", "source_user_id": 15438913, "source_user_id_str": "15438913", "type": "photo", "url": "http://t.co/2iqNZDfnEK"}], "symbols": [], "urls": [{"display_url": "dailym.ai/1wvbysG", "expanded_url": "http://dailym.ai/1wvbysG", "indices": [85, 107], "url": "http://t.co/NyKQtIsJNC"}], "user_mentions": [{"id": 15438913, "id_str": "15438913", "indices": [1, 12], "name": "Daily Mail Online", "screen_name": "MailOnline"}]}, "extended_entities": {"media": [{"display_url": "pic.twitter.com/2iqNZDfnEK", "expanded_url": "https://twitter.com/MailOnline/status/553108804934856704/photo/1", "id": 553108548968644600, "id_str": "553108548968644608", "indices": [108, 130], "media_url": "http://pbs.twimg.com/media/B60JS3eCAAAXCiC.jpg", "media_url_https": "https://pbs.twimg.com/media/B60JS3eCAAAXCiC.jpg", "sizes": {"large": {"h": 656, "resize": "fit", "w": 962}, "medium": {"h": 656, "resize": "fit", "w": 962}, "small": {"h": 464, "resize": "fit", "w": 680}, "thumb": {"h": 150, "resize": "crop", "w": 150}}, "source_status_id": 553108804934856700, "source_status_id_str": "553108804934856704", "source_user_id": 15438913, "source_user_id_str": "15438913", "type": "photo", "url": "http://t.co/2iqNZDfnEK"}, {"display_url": "pic.twitter.com/2iqNZDfnEK", "expanded_url": "https://twitter.com/MailOnline/status/553108804934856704/photo/1", "id": 553108549224517600, "id_str": "553108549224517633", "indices": [108, 130], "media_url": "http://pbs.twimg.com/media/B60JS4bCUAEopyK.jpg", "media_url_https": "https://pbs.twimg.com/media/B60JS4bCUAEopyK.jpg", "sizes": {"large": {"h": 1120, "resize": "fit", "w": 962}, "medium": {"h": 1120, "resize": "fit", "w": 962}, "small": {"h": 680, "resize": "fit", "w": 584}, "thumb": {"h": 150, "resize": "crop", "w": 150}}, "source_status_id": 553108804934856700, "source_status_id_str": "553108804934856704", "source_user_id": 15438913, "source_user_id_str": "15438913", "type": "photo", "url": "http://t.co/2iqNZDfnEK"}, {"display_url": "pic.twitter.com/2iqNZDfnEK", "expanded_url": "https://twitter.com/MailOnline/status/553108804934856704/photo/1", "id": 553108547815215100, "id_str": "553108547815215104", "indices": [108, 130], "media_url": "http://pbs.twimg.com/media/B60JSzLCEAAdkYi.jpg", "media_url_https": "https://pbs.twimg.com/media/B60JSzLCEAAdkYi.jpg", "sizes": {"large": {"h": 571, "resize": "fit", "w": 962}, "medium": {"h": 571, "resize": "fit", "w": 962}, "small": {"h": 404, "resize": "fit", "w": 680}, "thumb": {"h": 150, "resize": "crop", "w": 150}}, "source_status_id": 553108804934856700, "source_status_id_str": "553108804934856704", "source_user_id": 15438913, "source_user_id_str": "15438913", "type": "photo", "url": "http://t.co/2iqNZDfnEK"}, {"display_url": "pic.twitter.com/2iqNZDfnEK", "expanded_url": "https://twitter.com/MailOnline/status/553108804934856704/photo/1", "id": 553108548956065800, "id_str": "553108548956065793", "indices": [108, 130], "media_url": "http://pbs.twimg.com/media/B60JS3bCEAE1cmB.jpg", "media_url_https": "https://pbs.twimg.com/media/B60JS3bCEAE1cmB.jpg", "sizes": {"large": {"h": 769, "resize": "fit", "w": 962}, "medium": {"h": 769, "resize": "fit", "w": 962}, "small": {"h": 544, "resize": "fit", "w": 680}, "thumb": {"h": 150, "resize": "crop", "w": 150}}, "source_status_id": 553108804934856700, "source_status_id_str": "553108804934856704", "source_user_id": 15438913, "source_user_id_str": "15438913", "type": "photo", "url": "http://t.co/2iqNZDfnEK"}]}, "favorite_count": 0, "favorited": false, "full_text": "\u201c@MailOnline: World's artists react to #CharlieHebdo massacre with powerful drawings http://t.co/NyKQtIsJNC http://t.co/2iqNZDfnEK\u201d", "geo": null, "id": 553113369008295940, "id_str": "553113369008295936", "in_reply_to_screen_name": "MailOnline", "in_reply_to_status_id": 553108804934856700, "in_reply_to_status_id_str": "553108804934856704", "in_reply_to_user_id": 15438913, "in_reply_to_user_id_str": "15438913", "is_quote_status": false, "lang": "en", "place": null, "possibly_sensitive": false, "retweet_count": 0, "retweeted": false, "source": "<a href=\"http://twitter.com/#!/download/ipad\" rel=\"nofollow\">Twitter for iPad</a>", "truncated": false, "user": {"contributors_enabled": false, "created_at": "Wed Mar 20 23:23:20 +0000 2013", "default_profile": true, "default_profile_image": false, "description": "Retired, Viet Nam Vet,Happily married to the best woman I ever met! Son of WWII Vet, Grandson of WWI Vet.", "entities": {"description": {"urls": []}}, "favourites_count": 20008, "follow_request_sent": false, "followers_count": 1759, "following": false, "friends_count": 2503, "geo_enabled": false, "has_extended_profile": false, "id": 1284545959, "id_str": "1284545959", "is_translation_enabled": false, "is_translator": false, "lang": null, "listed_count": 63, "location": "So. Calif.", "name": "n.j.hokanson", "notifications": false, "profile_background_color": "C0DEED", "profile_background_image_url": "http://abs.twimg.com/images/themes/theme1/bg.png", "profile_background_image_url_https": "https://abs.twimg.com/images/themes/theme1/bg.png", "profile_background_tile": false, "profile_banner_url": "https://pbs.twimg.com/profile_banners/1284545959/1481140704", "profile_image_url": "http://pbs.twimg.com/profile_images/908808404457496576/FH8b6zwD_normal.jpg", "profile_image_url_https": "https://pbs.twimg.com/profile_images/908808404457496576/FH8b6zwD_normal.jpg", "profile_link_color": "1DA1F2", "profile_sidebar_border_color": "C0DEED", "profile_sidebar_fill_color": "DDEEF6", "profile_text_color": "333333", "profile_use_background_image": true, "protected": false, "screen_name": "Hokey1951", "statuses_count": 27735, "time_zone": null, "translator_type": "none", "url": null, "utc_offset": null, "verified": false}}