{"contributors": null, "coordinates": null, "created_at": "Thu Oct 23 14:25:43 +0000 2014", "display_text_range": [0, 140], "entities": {"hashtags": [], "symbols": [], "urls": [], "user_mentions": [{"id": 2760508119, "id_str": "2760508119", "indices": [0, 11], "name": "Michael Berardi", "screen_name": "BerardiXHS"}, {"id": 759251, "id_str": "759251", "indices": [12, 16], "name": "CNN", "screen_name": "CNN"}]}, "favorite_count": 0, "favorited": false, "full_text": "@BerardiXHS @CNN \n\nThat they are going to lockdown the city so no one can get out or in and they will find the person who killed that person", "geo": null, "id": 525291987726262300, "id_str": "525291987726262272", "in_reply_to_screen_name": "BerardiXHS", "in_reply_to_status_id": 525284149645819900, "in_reply_to_status_id_str": "525284149645819904", "in_reply_to_user_id": 2760508119, "in_reply_to_user_id_str": "2760508119", "is_quote_status": false, "lang": "en", "place": null, "retweet_count": 0, "retweeted": false, "source": "<a href=\"http://twitter.com/#!/download/ipad\" rel=\"nofollow\">Twitter for iPad</a>", "truncated": false, "user": {"contributors_enabled": false, "created_at": "Fri Sep 05 15:25:47 +0000 2014", "default_profile": true, "default_profile_image": false, "description": "", "entities": {"description": {"urls": []}}, "favourites_count": 2, "follow_request_sent": false, "followers_count": 23, "following": false, "friends_count": 19, "geo_enabled": false, "has_extended_profile": false, "id": 2762056102, "id_str": "2762056102", "is_translation_enabled": false, "is_translator": false, "lang": null, "listed_count": 0, "location": "", "name": "Jay Pantoja ", "notifications": false, "profile_background_color": "C0DEED", "profile_background_image_url": "http://abs.twimg.com/images/themes/theme1/bg.png", "profile_background_image_url_https": "https://abs.twimg.com/images/themes/theme1/bg.png", "profile_background_tile": false, "profile_banner_url": "https://pbs.twimg.com/profile_banners/2762056102/1409960041", "profile_image_url": "http://pbs.twimg.com/profile_images/508347345634066432/RuytfxVj_normal.jpeg", "profile_image_url_https": "https://pbs.twimg.com/profile_images/508347345634066432/RuytfxVj_normal.jpeg", "profile_link_color": "1DA1F2", "profile_sidebar_border_color": "C0DEED", "profile_sidebar_fill_color": "DDEEF6", "profile_text_color": "333333", "profile_use_background_image": true, "protected": false, "screen_name": "JPantojaXHS", "statuses_count": 33, "time_zone": null, "translator_type": "none", "url": null, "utc_offset": null, "verified": false}}