{"contributors": null, "coordinates": null, "created_at": "Wed Oct 01 11:05:27 +0000 2014", "display_text_range": [0, 20], "entities": {"hashtags": [], "symbols": [], "urls": [], "user_mentions": [{"id": 274407179, "id_str": "274407179", "indices": [0, 13], "name": "Jin Akanishi  \u8d64\u897f \u4ec1", "screen_name": "Jin_Akanishi"}]}, "favorite_count": 0, "favorited": false, "full_text": "@Jin_Akanishi \u306f\u3088\u306f\u3088\u2661\u2661", "geo": null, "id": 517269052201267200, "id_str": "517269052201267200", "in_reply_to_screen_name": "Jin_Akanishi", "in_reply_to_status_id": 517255163073937400, "in_reply_to_status_id_str": "517255163073937408", "in_reply_to_user_id": 274407179, "in_reply_to_user_id_str": "274407179", "is_quote_status": false, "lang": "ja", "place": null, "retweet_count": 0, "retweeted": false, "source": "<a href=\"http://twitter.com/download/iphone\" rel=\"nofollow\">Twitter for iPhone</a>", "truncated": false, "user": {"contributors_enabled": false, "created_at": "Mon Mar 10 11:44:30 +0000 2014", "default_profile": true, "default_profile_image": false, "description": "", "entities": {"description": {"urls": []}}, "favourites_count": 2434, "follow_request_sent": false, "followers_count": 34, "following": false, "friends_count": 101, "geo_enabled": false, "has_extended_profile": false, "id": 2382017594, "id_str": "2382017594", "is_translation_enabled": false, "is_translator": false, "lang": null, "listed_count": 4, "location": "", "name": "\u308b\u3045\u2661\u266c", "notifications": false, "profile_background_color": "C0DEED", "profile_background_image_url": "http://abs.twimg.com/images/themes/theme1/bg.png", "profile_background_image_url_https": "https://abs.twimg.com/images/themes/theme1/bg.png", "profile_background_tile": false, "profile_banner_url": "https://pbs.twimg.com/profile_banners/2382017594/1398504203", "profile_image_url": "http://pbs.twimg.com/profile_images/459985508215443456/k0SF0-6K_normal.jpeg", "profile_image_url_https": "https://pbs.twimg.com/profile_images/459985508215443456/k0SF0-6K_normal.jpeg", "profile_link_color": "1DA1F2", "profile_sidebar_border_color": "C0DEED", "profile_sidebar_fill_color": "DDEEF6", "profile_text_color": "333333", "profile_use_background_image": true, "protected": false, "screen_name": "2msb_3", "statuses_count": 2497, "time_zone": null, "translator_type": "none", "url": null, "utc_offset": null, "verified": false}}