{"contributors": null, "coordinates": null, "created_at": "Mon Apr 15 22:53:24 +0000 2013", "display_text_range": [0, 20], "entities": {"hashtags": [], "symbols": [], "urls": [], "user_mentions": [{"id": 206251633, "id_str": "206251633", "indices": [0, 16], "name": "Michael Del Zotto", "screen_name": "MichaelDelZotto"}]}, "favorite_count": 0, "favorited": false, "full_text": "@MichaelDelZotto \ud83d\ude4f\ud83d\ude4f\ud83d\ude4f", "geo": null, "id": 323932095510622200, "id_str": "323932095510622208", "in_reply_to_screen_name": "MichaelDelZotto", "in_reply_to_status_id": 323917397994135550, "in_reply_to_status_id_str": "323917397994135552", "in_reply_to_user_id": 206251633, "in_reply_to_user_id_str": "206251633", "is_quote_status": false, "lang": "und", "place": null, "retweet_count": 0, "retweeted": false, "source": "<a href=\"http://twitter.com/download/iphone\" rel=\"nofollow\">Twitter for iPhone</a>", "truncated": false, "user": {"contributors_enabled": false, "created_at": "Tue Aug 02 18:43:57 +0000 2011", "default_profile": false, "default_profile_image": false, "description": "SINGER, ACTRESS, BIKINI PRO, MODEL, BSN ATHLETE , FITNESS GIRLS ATHLETE\ud83d\ude0e\ud83d\udcaa\ud83c\udffd\ud83c\udf4cLOVE AND LIGHT TO ALL \u2600\ufe0f", "entities": {"description": {"urls": []}, "url": {"urls": [{"display_url": "ali-lee.com", "expanded_url": "http://www.ali-lee.com", "indices": [0, 23], "url": "https://t.co/VODnv5b618"}]}}, "favourites_count": 3418, "follow_request_sent": false, "followers_count": 10021, "following": false, "friends_count": 783, "geo_enabled": false, "has_extended_profile": false, "id": 347392852, "id_str": "347392852", "is_translation_enabled": false, "is_translator": false, "lang": null, "listed_count": 67, "location": "L.A. /NYC/MIAMI", "name": "ALI LEE", "notifications": false, "profile_background_color": "FFFFFF", "profile_background_image_url": "http://abs.twimg.com/images/themes/theme1/bg.png", "profile_background_image_url_https": "https://abs.twimg.com/images/themes/theme1/bg.png", "profile_background_tile": false, "profile_image_url": "http://pbs.twimg.com/profile_images/2891373373/4ea0a3b5dd731df623f56570dee444e9_normal.jpeg", "profile_image_url_https": "https://pbs.twimg.com/profile_images/2891373373/4ea0a3b5dd731df623f56570dee444e9_normal.jpeg", "profile_link_color": "0084B4", "profile_sidebar_border_color": "FFFFFF", "profile_sidebar_fill_color": "DDEEF6", "profile_text_color": "333333", "profile_use_background_image": true, "protected": false, "screen_name": "TheRealAliLee", "statuses_count": 7785, "time_zone": null, "translator_type": "none", "url": "https://t.co/VODnv5b618", "utc_offset": null, "verified": false}}