{"contributors": null, "coordinates": null, "created_at": "Mon Apr 15 20:00:22 +0000 2013", "display_text_range": [0, 22], "entities": {"hashtags": [], "symbols": [], "urls": [], "user_mentions": [{"id": 150846769, "id_str": "150846769", "indices": [11, 22], "name": "Rajon Rondo", "screen_name": "RajonRondo"}]}, "favorite_count": 0, "favorited": false, "full_text": "Hi sexxxy .@rajonrondo", "geo": null, "id": 323888550816931840, "id_str": "323888550816931840", "in_reply_to_screen_name": "RajonRondo", "in_reply_to_status_id": 323888145282256900, "in_reply_to_status_id_str": "323888145282256898", "in_reply_to_user_id": 150846769, "in_reply_to_user_id_str": "150846769", "is_quote_status": false, "lang": "en", "place": null, "retweet_count": 0, "retweeted": false, "source": "<a href=\"https://mobile.twitter.com\" rel=\"nofollow\">Mobile Web (M2)</a>", "truncated": false, "user": {"contributors_enabled": false, "created_at": "Tue Mar 27 14:23:39 +0000 2012", "default_profile": false, "default_profile_image": false, "description": "I'm getn it out tha h.I am an songwriter/singer,I rite books,an actress,model,&aclothing line start'n.look out for tha best at what I do.", "entities": {"description": {"urls": []}}, "favourites_count": 2965, "follow_request_sent": false, "followers_count": 387, "following": false, "friends_count": 1272, "geo_enabled": true, "has_extended_profile": false, "id": 538199909, "id_str": "538199909", "is_translation_enabled": false, "is_translator": false, "lang": null, "listed_count": 4, "location": "h/town soon your town", "name": "Queen ChicaYummie", "notifications": false, "profile_background_color": "0099B9", "profile_background_image_url": "http://abs.twimg.com/images/themes/theme4/bg.gif", "profile_background_image_url_https": "https://abs.twimg.com/images/themes/theme4/bg.gif", "profile_background_tile": false, "profile_image_url": "http://pbs.twimg.com/profile_images/1978494960/tif1_normal.jpg", "profile_image_url_https": "https://pbs.twimg.com/profile_images/1978494960/tif1_normal.jpg", "profile_link_color": "0099B9", "profile_sidebar_border_color": "5ED4DC", "profile_sidebar_fill_color": "95E8EC", "profile_text_color": "3C3940", "profile_use_background_image": true, "protected": false, "screen_name": "Tha1stBarbieYum", "statuses_count": 19870, "time_zone": null, "translator_type": "none", "url": null, "utc_offset": null, "verified": false}}