{"contributors": null, "coordinates": null, "created_at": "Mon Apr 15 22:52:46 +0000 2013", "display_text_range": [0, 48], "entities": {"hashtags": [], "symbols": [], "urls": [], "user_mentions": [{"id": 473469791, "id_str": "473469791", "indices": [0, 15], "name": "Carly Rose", "screen_name": "CarlyRoseMusic"}]}, "favorite_count": 0, "favorited": false, "full_text": "@CarlyRoseMusic follow mee please \u2665 I love you \u263a", "geo": null, "id": 323931937771225100, "id_str": "323931937771225089", "in_reply_to_screen_name": "CarlyRoseMusic", "in_reply_to_status_id": 323930618540994560, "in_reply_to_status_id_str": "323930618540994560", "in_reply_to_user_id": 473469791, "in_reply_to_user_id_str": "473469791", "is_quote_status": false, "lang": "en", "place": null, "retweet_count": 0, "retweeted": false, "source": "<a href=\"http://blackberry.com/twitter\" rel=\"nofollow\">Twitter for BlackBerry\u00ae</a>", "truncated": false, "user": {"contributors_enabled": false, "created_at": "Sun Mar 18 17:15:10 +0000 2012", "default_profile": false, "default_profile_image": false, "description": "Midnight Memories", "entities": {"description": {"urls": []}}, "favourites_count": 97, "follow_request_sent": false, "followers_count": 598, "following": false, "friends_count": 1481, "geo_enabled": true, "has_extended_profile": false, "id": 528680166, "id_str": "528680166", "is_translation_enabled": false, "is_translator": false, "lang": null, "listed_count": 0, "location": "", "name": "wut?", "notifications": false, "profile_background_color": "FFFFFF", "profile_background_image_url": "http://abs.twimg.com/images/themes/theme18/bg.gif", "profile_background_image_url_https": "https://abs.twimg.com/images/themes/theme18/bg.gif", "profile_background_tile": false, "profile_banner_url": "https://pbs.twimg.com/profile_banners/528680166/1368042456", "profile_image_url": "http://pbs.twimg.com/profile_images/3632164923/f278900bbe662a4d508ac9151b9e71bf_normal.jpeg", "profile_image_url_https": "https://pbs.twimg.com/profile_images/3632164923/f278900bbe662a4d508ac9151b9e71bf_normal.jpeg", "profile_link_color": "DB29FF", "profile_sidebar_border_color": "FFFFFF", "profile_sidebar_fill_color": "F6F6F6", "profile_text_color": "333333", "profile_use_background_image": true, "protected": false, "screen_name": "NiallerSmilee", "statuses_count": 3200, "time_zone": null, "translator_type": "regular", "url": null, "utc_offset": null, "verified": false}}