{"contributors": null, "coordinates": null, "created_at": "Sun May 18 05:28:10 +0000 2014", "display_text_range": [0, 65], "entities": {"hashtags": [], "media": [{"display_url": "pic.twitter.com/Bqe9SKJbaZ", "expanded_url": "https://twitter.com/5SOS/status/467803895746412545/photo/1", "id": 467803894144581600, "id_str": "467803894144581632", "indices": [35, 57], "media_url": "http://pbs.twimg.com/media/Bn35KccIQAAFE_D.jpg", "media_url_https": "https://pbs.twimg.com/media/Bn35KccIQAAFE_D.jpg", "sizes": {"large": {"h": 700, "resize": "fit", "w": 500}, "medium": {"h": 700, "resize": "fit", "w": 500}, "small": {"h": 680, "resize": "fit", "w": 486}, "thumb": {"h": 150, "resize": "crop", "w": 150}}, "source_status_id": 467803895746412540, "source_status_id_str": "467803895746412545", "source_user_id": 264107729, "source_user_id_str": "264107729", "type": "photo", "url": "http://t.co/Bqe9SKJbaZ"}], "symbols": [], "urls": [], "user_mentions": [{"id": 264107729, "id_str": "264107729", "indices": [1, 6], "name": "5 Seconds Of Summer", "screen_name": "5SOS"}]}, "extended_entities": {"media": [{"display_url": "pic.twitter.com/Bqe9SKJbaZ", "expanded_url": "https://twitter.com/5SOS/status/467803895746412545/photo/1", "id": 467803894144581600, "id_str": "467803894144581632", "indices": [35, 57], "media_url": "http://pbs.twimg.com/media/Bn35KccIQAAFE_D.jpg", "media_url_https": "https://pbs.twimg.com/media/Bn35KccIQAAFE_D.jpg", "sizes": {"large": {"h": 700, "resize": "fit", "w": 500}, "medium": {"h": 700, "resize": "fit", "w": 500}, "small": {"h": 680, "resize": "fit", "w": 486}, "thumb": {"h": 150, "resize": "crop", "w": 150}}, "source_status_id": 467803895746412540, "source_status_id_str": "467803895746412545", "source_user_id": 264107729, "source_user_id_str": "264107729", "type": "photo", "url": "http://t.co/Bqe9SKJbaZ"}]}, "favorite_count": 1, "favorited": false, "full_text": "\u201c@5SOS: Me and Mikey in Sydney! :) http://t.co/Bqe9SKJbaZ\u201d cuties", "geo": null, "id": 467899424149364740, "id_str": "467899424149364736", "in_reply_to_screen_name": "5SOS", "in_reply_to_status_id": 467803895746412540, "in_reply_to_status_id_str": "467803895746412545", "in_reply_to_user_id": 264107729, "in_reply_to_user_id_str": "264107729", "is_quote_status": false, "lang": "en", "place": null, "possibly_sensitive": false, "retweet_count": 0, "retweeted": false, "source": "<a href=\"http://twitter.com/#!/download/ipad\" rel=\"nofollow\">Twitter for iPad</a>", "truncated": false, "user": {"contributors_enabled": false, "created_at": "Thu Apr 11 18:51:28 +0000 2013", "default_profile": false, "default_profile_image": false, "description": "just keep on truckin' \ud83c\udf41 [ \u00be + \u24d1\u24d0\u24dd\u24d3 ]", "entities": {"description": {"urls": []}}, "favourites_count": 17627, "follow_request_sent": false, "followers_count": 15431, "following": false, "friends_count": 952, "geo_enabled": false, "has_extended_profile": false, "id": 1345054195, "id_str": "1345054195", "is_translation_enabled": false, "is_translator": false, "lang": null, "listed_count": 62, "location": "england/wales", "name": "red", "notifications": false, "profile_background_color": "FFFFFF", "profile_background_image_url": "http://abs.twimg.com/images/themes/theme1/bg.png", "profile_background_image_url_https": "https://abs.twimg.com/images/themes/theme1/bg.png", "profile_background_tile": true, "profile_banner_url": "https://pbs.twimg.com/profile_banners/1345054195/1444941105", "profile_image_url": "http://pbs.twimg.com/profile_images/651816515428335616/976CUvBP_normal.jpg", "profile_image_url_https": "https://pbs.twimg.com/profile_images/651816515428335616/976CUvBP_normal.jpg", "profile_link_color": "1C961E", "profile_sidebar_border_color": "FFFFFF", "profile_sidebar_fill_color": "DDEEF6", "profile_text_color": "333333", "profile_use_background_image": true, "protected": false, "screen_name": "Red5SOS", "statuses_count": 48200, "time_zone": null, "translator_type": "regular", "url": null, "utc_offset": null, "verified": false}}