{"contributors": null, "coordinates": null, "created_at": "Mon Dec 15 03:37:55 +0000 2014", "display_text_range": [0, 67], "entities": {"hashtags": [], "symbols": [], "urls": [], "user_mentions": [{"id": 79009461, "id_str": "79009461", "indices": [0, 14], "name": "Jessica Plautz", "screen_name": "jessicaplautz"}, {"id": 25375836, "id_str": "25375836", "indices": [15, 29], "name": "Erin *crosstalk* Ryan", "screen_name": "morninggloria"}, {"id": 19103481, "id_str": "19103481", "indices": [30, 35], "name": "Uber", "screen_name": "Uber"}, {"id": 972651, "id_str": "972651", "indices": [36, 45], "name": "Mashable", "screen_name": "mashable"}]}, "favorite_count": 0, "favorited": false, "full_text": "@jessicaplautz @morninggloria @Uber @mashable oof they are terrible", "geo": null, "id": 544335520307118100, "id_str": "544335520307118080", "in_reply_to_screen_name": "jessicaplautz", "in_reply_to_status_id": 544314160864317440, "in_reply_to_status_id_str": "544314160864317441", "in_reply_to_user_id": 79009461, "in_reply_to_user_id_str": "79009461", "is_quote_status": false, "lang": "en", "place": null, "retweet_count": 0, "retweeted": false, "source": "<a href=\"http://twitter.com/download/iphone\" rel=\"nofollow\">Twitter for iPhone</a>", "truncated": false, "user": {"contributors_enabled": false, "created_at": "Fri Sep 03 16:46:08 +0000 2010", "default_profile": false, "default_profile_image": false, "description": "I pronounce the t in 'often'. Favorite TV Show: Scrubs. Favorite Song: No Scrubs. Most controversial position: Fascism is bad.", "entities": {"description": {"urls": []}}, "favourites_count": 358672, "follow_request_sent": false, "followers_count": 3282, "following": false, "friends_count": 625, "geo_enabled": false, "has_extended_profile": false, "id": 186501062, "id_str": "186501062", "is_translation_enabled": false, "is_translator": false, "lang": null, "listed_count": 81, "location": "", "name": "Grudge of Whales", "notifications": false, "profile_background_color": "000000", "profile_background_image_url": "http://abs.twimg.com/images/themes/theme1/bg.png", "profile_background_image_url_https": "https://abs.twimg.com/images/themes/theme1/bg.png", "profile_background_tile": false, "profile_banner_url": "https://pbs.twimg.com/profile_banners/186501062/1485188181", "profile_image_url": "http://pbs.twimg.com/profile_images/909236929522229249/IqVXpXDZ_normal.jpg", "profile_image_url_https": "https://pbs.twimg.com/profile_images/909236929522229249/IqVXpXDZ_normal.jpg", "profile_link_color": "ABB8C2", "profile_sidebar_border_color": "000000", "profile_sidebar_fill_color": "000000", "profile_text_color": "000000", "profile_use_background_image": false, "protected": false, "screen_name": "grudging1", "statuses_count": 136643, "time_zone": null, "translator_type": "none", "url": null, "utc_offset": null, "verified": false}}