{"contributors": null, "coordinates": null, "created_at": "Mon Jan 12 21:45:34 +0000 2015", "display_text_range": [0, 136], "entities": {"hashtags": [{"indices": [65, 79], "text": "JesuisCharlie"}, {"indices": [92, 105], "text": "CharlieHebdo"}], "media": [{"display_url": "pic.twitter.com/lcmpKZB3uk", "expanded_url": "https://twitter.com/libe/status/554752478630379523/photo/1", "id": 554752477846069250, "id_str": "554752477846069248", "indices": [114, 136], "media_url": "http://pbs.twimg.com/media/B7LgcHxIYAAforh.png", "media_url_https": "https://pbs.twimg.com/media/B7LgcHxIYAAforh.png", "sizes": {"large": {"h": 849, "resize": "fit", "w": 640}, "medium": {"h": 849, "resize": "fit", "w": 640}, "small": {"h": 680, "resize": "fit", "w": 513}, "thumb": {"h": 150, "resize": "crop", "w": 150}}, "source_status_id": 554752478630379500, "source_status_id_str": "554752478630379523", "source_user_id": 68440549, "source_user_id_str": "68440549", "type": "photo", "url": "http://t.co/lcmpKZB3uk"}], "symbols": [], "urls": [], "user_mentions": [{"id": 16827148, "id_str": "16827148", "indices": [26, 40], "name": "Christopher Miller", "screen_name": "ChristopherJM"}]}, "extended_entities": {"media": [{"display_url": "pic.twitter.com/lcmpKZB3uk", "expanded_url": "https://twitter.com/libe/status/554752478630379523/photo/1", "id": 554752477846069250, "id_str": "554752477846069248", "indices": [114, 136], "media_url": "http://pbs.twimg.com/media/B7LgcHxIYAAforh.png", "media_url_https": "https://pbs.twimg.com/media/B7LgcHxIYAAforh.png", "sizes": {"large": {"h": 849, "resize": "fit", "w": 640}, "medium": {"h": 849, "resize": "fit", "w": 640}, "small": {"h": 680, "resize": "fit", "w": 513}, "thumb": {"h": 150, "resize": "crop", "w": 150}}, "source_status_id": 554752478630379500, "source_status_id_str": "554752478630379523", "source_user_id": 68440549, "source_user_id_str": "68440549", "type": "photo", "url": "http://t.co/lcmpKZB3uk"}]}, "favorite_count": 0, "favorited": false, "full_text": "Tomorrow's front page. RT @ChristopherJM: Prophet Mohammed holds #JesuisCharlie sign in new #CharlieHebdo cartoon http://t.co/lcmpKZB3uk", "geo": null, "id": 554756094590205950, "id_str": "554756094590205952", "in_reply_to_screen_name": "ChristopherJM", "in_reply_to_status_id": 554754998090096640, "in_reply_to_status_id_str": "554754998090096640", "in_reply_to_user_id": 16827148, "in_reply_to_user_id_str": "16827148", "is_quote_status": false, "lang": "en", "place": null, "possibly_sensitive": false, "retweet_count": 1, "retweeted": false, "source": "<a href=\"http://twitter.com/download/iphone\" rel=\"nofollow\">Twitter for iPhone</a>", "truncated": false, "user": {"contributors_enabled": false, "created_at": "Tue Dec 01 23:00:40 +0000 2009", "default_profile": false, "default_profile_image": false, "description": "Writer/columnist. Feminist. Bylines: @nytimes, @thecut, @macleans, @msmagazine, @NatObserver, @huffpost, @ricochet_en, @BuzzFeed, @nationalpost. \ud83d\udcfa:@mAtv_MTL", "entities": {"description": {"urls": []}, "url": {"urls": [{"display_url": "headspacepress.com", "expanded_url": "http://www.headspacepress.com", "indices": [0, 23], "url": "https://t.co/SOt0l87kL7"}]}}, "favourites_count": 20397, "follow_request_sent": false, "followers_count": 6489, "following": false, "friends_count": 3251, "geo_enabled": true, "has_extended_profile": false, "id": 93964759, "id_str": "93964759", "is_translation_enabled": false, "is_translator": false, "lang": null, "listed_count": 206, "location": "Montreal, Canada", "name": "Toula Drimonis", "notifications": false, "profile_background_color": "C0DEED", "profile_background_image_url": "http://abs.twimg.com/images/themes/theme1/bg.png", "profile_background_image_url_https": "https://abs.twimg.com/images/themes/theme1/bg.png", "profile_background_tile": false, "profile_banner_url": "https://pbs.twimg.com/profile_banners/93964759/1413565500", "profile_image_url": "http://pbs.twimg.com/profile_images/523156232748924928/U8SWv7dC_normal.jpeg", "profile_image_url_https": "https://pbs.twimg.com/profile_images/523156232748924928/U8SWv7dC_normal.jpeg", "profile_link_color": "0084B4", "profile_sidebar_border_color": "C0DEED", "profile_sidebar_fill_color": "DDEEF6", "profile_text_color": "333333", "profile_use_background_image": true, "protected": false, "screen_name": "ToulasTake", "statuses_count": 62581, "time_zone": null, "translator_type": "none", "url": "https://t.co/SOt0l87kL7", "utc_offset": null, "verified": false}}